LICENSE.txt
README.rst
setup.py
pygencad/SVGPan.js
pygencad/__init__.py
pygencad/autocad.py
pygencad/commandfile.py
pygencad/commands.py
pygencad/microstation.py
pygencad/svg.py
pygencad.egg-info/PKG-INFO
pygencad.egg-info/SOURCES.txt
pygencad.egg-info/dependency_links.txt
pygencad.egg-info/not-zip-safe
pygencad.egg-info/top_level.txt